madagscar/__init__.py
madagascar-0.1.1.dist-info/LICENSE
madagascar-0.1.1.dist-info/METADATA
madagascar-0.1.1.dist-info/WHEEL
madagascar-0.1.1.dist-info/top_level.txt
madagascar-0.1.1.dist-info/RECORD
